mdf_connect_client/__init__.py
mdf_connect_client/mdfcc.py
mdf_connect_client/version.py
mdf_connect_client-0.5.0.dist-info/LICENSE
mdf_connect_client-0.5.0.dist-info/METADATA
mdf_connect_client-0.5.0.dist-info/NOTICE
mdf_connect_client-0.5.0.dist-info/WHEEL
mdf_connect_client-0.5.0.dist-info/top_level.txt
mdf_connect_client-0.5.0.dist-info/RECORD
