Metadata-Version: 2.1
Name: mdf_connect_client
Version: 0.5.0
Summary: Materials Data Facility Connect Client
Home-page: https://github.com/materials-data-facility/connect_client
License: Apache License, Version 2.0
Keywords: MDF,Materials Data Facility,materials science,utility,Connect Client
Classifier: Development Status :: 3 - Alpha
Classifier: License :: OSI Approved :: Apache Software License
Classifier: Natural Language :: English
Classifier: Operating System :: OS Independent
Classifier: Programming Language :: Python :: 3
Requires-Python: >=3.5
License-File: LICENSE
License-File: NOTICE
Requires-Dist: mdf-toolbox >=0.7.1
Requires-Dist: nameparser >=1.0.4
Requires-Dist: requests >=2.18.4
